kytchen/__init__.py
kytchen/cli.py
kytchen/config.py
kytchen/core.py
kytchen/recipe.py
kytchen/types.py
kytchen/api/__init__.py
kytchen/api/app.py
kytchen/api/audit.py
kytchen/api/auth.py
kytchen/api/db.py
kytchen/api/keys.py
kytchen/api/limits.py
kytchen/api/models.py
kytchen/api/processing.py
kytchen/api/state.py
kytchen/api/storage.py
kytchen/api/routes/__init__.py
kytchen/api/routes/auth.py
kytchen/api/routes/billing.py
kytchen/api/routes/git.py
kytchen/api/routes/keys.py
kytchen/api/routes/kytchens.py
kytchen/api/routes/lines.py
kytchen/api/schemas/__init__.py
kytchen/api/schemas/kitchen.py
kytchen/api/schemas/kytchen.py
kytchen/api/schemas/menu.py
kytchen/api/schemas/ticket.py
kytchen/cache/__init__.py
kytchen/cache/base.py
kytchen/cache/memory.py
kytchen/cache/ttl_memory.py
kytchen/cli/README.md
kytchen/cli/__init__.py
kytchen/cli/auth.py
kytchen/cli/completion.py
kytchen/cli/config_cmd.py
kytchen/cli/doctor.py
kytchen/cli/export_cmd.py
kytchen/cli/git.py
kytchen/cli/init_cmd.py
kytchen/cli/keys.py
kytchen/cli/main.py
kytchen/cli/mcp.py
kytchen/cli/query.py
kytchen/cli/workspace.py
kytchen/cli/utils/__init__.py
kytchen/cli/utils/api_client.py
kytchen/cli/utils/config_loader.py
kytchen/cli/utils/credentials.py
kytchen/cli/utils/output.py
kytchen/converters/__init__.py
kytchen/converters/docx.py
kytchen/converters/image.py
kytchen/converters/pages.py
kytchen/converters/pdf.py
kytchen/converters/xlsx.py
kytchen/exporters/__init__.py
kytchen/exporters/markdown.py
kytchen/exporters/pdf.py
kytchen/mcp/__init__.py
kytchen/mcp/cloud_client.py
kytchen/mcp/local_server.py
kytchen/mcp/server.py
kytchen/prompts/__init__.py
kytchen/prompts/system.py
kytchen/providers/__init__.py
kytchen/providers/anthropic.py
kytchen/providers/base.py
kytchen/providers/openai.py
kytchen/providers/registry.py
kytchen/repl/__init__.py
kytchen/repl/helpers.py
kytchen/repl/sandbox.py
kytchen/sandbox/__init__.py
kytchen/sandbox/e2b.py
kytchen/sandbox/local.py
kytchen/scripts/__init__.py
kytchen_rlm-1.0.0.dist-info/METADATA
kytchen_rlm-1.0.0.dist-info/WHEEL
kytchen_rlm-1.0.0.dist-info/entry_points.txt
kytchen_rlm-1.0.0.dist-info/licenses/LICENSE
kytchen_rlm-1.0.0.dist-info/RECORD
