Metadata-Version: 2.4
Name: kytchen-rlm
Version: 1.0.0
Summary: Kytchen RLM - Recursive Language Models with BYOLLM pantry storage + sandboxed prep + sauce (audit trail)
Project-URL: Homepage, https://kytchen.dev
Project-URL: Repository, https://github.com/shannon-labs/kytchen
Author: Shannon Labs
License: MIT License
License-File: LICENSE
Requires-Python: >=3.10
Requires-Dist: httpx>=0.27.0
Provides-Extra: api
Requires-Dist: asyncpg>=0.29.0; extra == 'api'
Requires-Dist: fastapi>=0.110.0; extra == 'api'
Requires-Dist: minio>=7.2.0; extra == 'api'
Requires-Dist: python-multipart>=0.0.9; extra == 'api'
Requires-Dist: sentry-sdk[fastapi]>=2.0.0; extra == 'api'
Requires-Dist: sqlalchemy[asyncio]>=2.0.0; extra == 'api'
Requires-Dist: stripe>=7.0.0; extra == 'api'
Requires-Dist: uvicorn>=0.27.0; extra == 'api'
Provides-Extra: cli
Requires-Dist: keyring>=25.0.0; extra == 'cli'
Requires-Dist: python-dotenv>=1.0.0; extra == 'cli'
Requires-Dist: questionary>=2.0.0; extra == 'cli'
Requires-Dist: rich>=13.0.0; extra == 'cli'
Requires-Dist: typer[all]>=0.12.0; extra == 'cli'
Provides-Extra: converters
Requires-Dist: openpyxl>=3.1; extra == 'converters'
Requires-Dist: pypdf>=4.0; extra == 'converters'
Requires-Dist: python-docx>=1.0; extra == 'converters'
Provides-Extra: dev
Requires-Dist: mypy>=1.8.0; extra == 'dev'
Requires-Dist: pytest-asyncio>=0.23.0; extra == 'dev'
Requires-Dist: pytest>=8.0.0; extra == 'dev'
Provides-Extra: e2b
Requires-Dist: e2b-code-interpreter>=0.0.11; extra == 'e2b'
Provides-Extra: exporters
Requires-Dist: markdown>=3.5.0; extra == 'exporters'
Provides-Extra: mcp
Requires-Dist: mcp>=1.0.0; extra == 'mcp'
Provides-Extra: ocr
Requires-Dist: pillow>=10.0; extra == 'ocr'
Requires-Dist: pytesseract>=0.3; extra == 'ocr'
Provides-Extra: openai-tokens
Requires-Dist: tiktoken>=0.7.0; extra == 'openai-tokens'
Provides-Extra: pdf
Requires-Dist: weasyprint>=60.0; extra == 'pdf'
Provides-Extra: pdf-simple
Requires-Dist: fpdf2>=2.7.0; extra == 'pdf-simple'
Provides-Extra: rich
Requires-Dist: rich>=13.0.0; extra == 'rich'
Provides-Extra: yaml
Requires-Dist: pyyaml>=6.0; extra == 'yaml'
